{"expireTime":9007200823643564000,"key":"transformer-remark-markdown-html-ast-99ae6940e1cfa68514658d943f4f7183-gatsby-remark-autolink-headersgatsby-remark-copy-linked-filesgatsby-remark-prismjs-","val":{"type":"root","children":[{"type":"element","tagName":"p","properties":{},"children":[{"type":"text","value":"The WCAG-ACT-RULES-CG rule design builds on WCAG 2.x and its supporting documents. To achieve the goals the following approach is suggested:","position":{"start":{"line":2,"column":1,"offset":1},"end":{"line":2,"column":141,"offset":141}}}],"position":{"start":{"line":2,"column":1,"offset":1},"end":{"line":2,"column":141,"offset":141}}},{"type":"text","value":"\n"},{"type":"element","tagName":"ol","properties":{},"children":[{"type":"text","value":"\n"},{"type":"element","tagName":"li","properties":{},"children":[{"type":"element","tagName":"strong","properties":{},"children":[{"type":"element","tagName":"a","properties":{"href":"#rule-properties"},"children":[{"type":"text","value":"Rule properties","position":{"start":{"line":4,"column":7,"offset":149},"end":{"line":4,"column":22,"offset":164}}}],"position":{"start":{"line":4,"column":6,"offset":148},"end":{"line":4,"column":41,"offset":183}}}],"position":{"start":{"line":4,"column":4,"offset":146},"end":{"line":4,"column":43,"offset":185}}},{"type":"text","value":": Define the test subject and its environment, as well as other meta data.","position":{"start":{"line":4,"column":43,"offset":185},"end":{"line":4,"column":117,"offset":259}}}],"position":{"start":{"line":4,"column":1,"offset":143},"end":{"line":5,"column":1,"offset":260}}},{"type":"text","value":"\n"},{"type":"element","tagName":"li","properties":{},"children":[{"type":"element","tagName":"strong","properties":{},"children":[{"type":"text","value":"Description","position":{"start":{"line":6,"column":6,"offset":266},"end":{"line":6,"column":17,"offset":277}}}],"position":{"start":{"line":6,"column":4,"offset":264},"end":{"line":6,"column":19,"offset":279}}},{"type":"text","value":": Brief description of what the rule does","position":{"start":{"line":6,"column":19,"offset":279},"end":{"line":6,"column":60,"offset":320}}}],"position":{"start":{"line":6,"column":1,"offset":261},"end":{"line":7,"column":1,"offset":321}}},{"type":"text","value":"\n"},{"type":"element","tagName":"li","properties":{},"children":[{"type":"element","tagName":"strong","properties":{},"children":[{"type":"text","value":"Background","position":{"start":{"line":8,"column":6,"offset":327},"end":{"line":8,"column":16,"offset":337}}}],"position":{"start":{"line":8,"column":4,"offset":325},"end":{"line":8,"column":18,"offset":339}}},{"type":"text","value":": A list of resources that support the workings of the rule.","position":{"start":{"line":8,"column":18,"offset":339},"end":{"line":8,"column":78,"offset":399}}}],"position":{"start":{"line":8,"column":1,"offset":322},"end":{"line":9,"column":1,"offset":400}}},{"type":"text","value":"\n"},{"type":"element","tagName":"li","properties":{},"children":[{"type":"element","tagName":"strong","properties":{},"children":[{"type":"element","tagName":"a","properties":{"href":"#assumptions"},"children":[{"type":"text","value":"Assumptions","position":{"start":{"line":10,"column":7,"offset":407},"end":{"line":10,"column":18,"offset":418}}}],"position":{"start":{"line":10,"column":6,"offset":406},"end":{"line":10,"column":33,"offset":433}}}],"position":{"start":{"line":10,"column":4,"offset":404},"end":{"line":10,"column":35,"offset":435}}},{"type":"text","value":": Explicitly state all assumptions made by the rule to ensure accountability of the results.","position":{"start":{"line":10,"column":35,"offset":435},"end":{"line":10,"column":127,"offset":527}}}],"position":{"start":{"line":10,"column":1,"offset":401},"end":{"line":11,"column":1,"offset":528}}},{"type":"text","value":"\n"},{"type":"element","tagName":"li","properties":{},"children":[{"type":"element","tagName":"strong","properties":{},"children":[{"type":"element","tagName":"a","properties":{"href":"#applicability"},"children":[{"type":"text","value":"Applicability","position":{"start":{"line":12,"column":7,"offset":535},"end":{"line":12,"column":20,"offset":548}}}],"position":{"start":{"line":12,"column":6,"offset":534},"end":{"line":12,"column":37,"offset":565}}}],"position":{"start":{"line":12,"column":4,"offset":532},"end":{"line":12,"column":39,"offset":567}}},{"type":"text","value":": Identify which elements on a page (if any) are to be tested using the rule.","position":{"start":{"line":12,"column":39,"offset":567},"end":{"line":12,"column":116,"offset":644}}}],"position":{"start":{"line":12,"column":1,"offset":529},"end":{"line":13,"column":1,"offset":645}}},{"type":"text","value":"\n"},{"type":"element","tagName":"li","properties":{},"children":[{"type":"element","tagName":"strong","properties":{},"children":[{"type":"element","tagName":"a","properties":{"href":"#expectations"},"children":[{"type":"text","value":"Expectations","position":{"start":{"line":14,"column":7,"offset":652},"end":{"line":14,"column":19,"offset":664}}}],"position":{"start":{"line":14,"column":6,"offset":651},"end":{"line":14,"column":35,"offset":680}}}],"position":{"start":{"line":14,"column":4,"offset":649},"end":{"line":14,"column":37,"offset":682}}},{"type":"text","value":": Assert what must be true about the target elements, in order for them to pass the rule.","position":{"start":{"line":14,"column":37,"offset":682},"end":{"line":14,"column":126,"offset":771}}}],"position":{"start":{"line":14,"column":1,"offset":646},"end":{"line":14,"column":126,"offset":771}}},{"type":"text","value":"\n"}],"position":{"start":{"line":4,"column":1,"offset":143},"end":{"line":14,"column":126,"offset":771}}},{"type":"text","value":"\n"},{"type":"element","tagName":"h2","properties":{"id":"rule-properties"},"children":[{"type":"element","tagName":"a","properties":{"href":"#rule-properties","aria-label":"rule properties permalink","class":"anchor"},"children":[{"type":"raw","value":"<svg aria-hidden=\"true\" focusable=\"false\" height=\"16\" version=\"1.1\" viewBox=\"0 0 16 16\" width=\"16\"><path fill-rule=\"evenodd\" d=\"M4 9h1v1H4c-1.5 0-3-1.69-3-3.5S2.55 3 4 3h4c1.45 0 3 1.69 3 3.5 0 1.41-.91 2.72-2 3.25V8.59c.58-.45 1-1.27 1-2.09C10 5.22 8.98 4 8 4H4c-.98 0-2 1.22-2 2.5S3 9 4 9zm9-3h-1v1h1c1 0 2 1.22 2 2.5S13.98 12 13 12H9c-.98 0-2-1.22-2-2.5 0-.83.42-1.64 1-2.09V6.25c-1.09.53-2 1.84-2 3.25C6 11.31 7.55 13 9 13h4c1.45 0 3-1.69 3-3.5S14.5 6 13 6z\"></path></svg>"}]},{"type":"text","value":"Rule Properties","position":{"start":{"line":16,"column":4,"offset":776},"end":{"line":16,"column":19,"offset":791}}}],"position":{"start":{"line":16,"column":1,"offset":773},"end":{"line":16,"column":19,"offset":791}}},{"type":"text","value":"\n"},{"type":"element","tagName":"h3","properties":{"id":"rule-name-and-identifier"},"children":[{"type":"element","tagName":"a","properties":{"href":"#rule-name-and-identifier","aria-label":"rule name and identifier permalink","class":"anchor"},"children":[{"type":"raw","value":"<svg aria-hidden=\"true\" focusable=\"false\" height=\"16\" version=\"1.1\" viewBox=\"0 0 16 16\" width=\"16\"><path fill-rule=\"evenodd\" d=\"M4 9h1v1H4c-1.5 0-3-1.69-3-3.5S2.55 3 4 3h4c1.45 0 3 1.69 3 3.5 0 1.41-.91 2.72-2 3.25V8.59c.58-.45 1-1.27 1-2.09C10 5.22 8.98 4 8 4H4c-.98 0-2 1.22-2 2.5S3 9 4 9zm9-3h-1v1h1c1 0 2 1.22 2 2.5S13.98 12 13 12H9c-.98 0-2-1.22-2-2.5 0-.83.42-1.64 1-2.09V6.25c-1.09.53-2 1.84-2 3.25C6 11.31 7.55 13 9 13h4c1.45 0 3-1.69 3-3.5S14.5 6 13 6z\"></path></svg>"}]},{"type":"text","value":"Rule name and identifier","position":{"start":{"line":18,"column":5,"offset":797},"end":{"line":18,"column":29,"offset":821}}}],"position":{"start":{"line":18,"column":1,"offset":793},"end":{"line":18,"column":29,"offset":821}}},{"type":"text","value":"\n"},{"type":"element","tagName":"p","properties":{},"children":[{"type":"text","value":"The rule must have a unique name, preferably a two or three word topic, as well as an identifier. This uses the following format: ","position":{"start":{"line":20,"column":1,"offset":823},"end":{"line":20,"column":131,"offset":953}}},{"type":"element","tagName":"strong","properties":{},"children":[{"type":"text","value":"SC#-#-#-identifier","position":{"start":{"line":20,"column":133,"offset":955},"end":{"line":20,"column":151,"offset":973}}}],"position":{"start":{"line":20,"column":131,"offset":953},"end":{"line":20,"column":153,"offset":975}}}],"position":{"start":{"line":20,"column":1,"offset":823},"end":{"line":20,"column":153,"offset":975}}},{"type":"text","value":"\n"},{"type":"element","tagName":"ul","properties":{},"children":[{"type":"text","value":"\n"},{"type":"element","tagName":"li","properties":{},"children":[{"type":"element","tagName":"strong","properties":{},"children":[{"type":"text","value":"SC#-#-#","position":{"start":{"line":22,"column":5,"offset":981},"end":{"line":22,"column":12,"offset":988}}}],"position":{"start":{"line":22,"column":3,"offset":979},"end":{"line":22,"column":14,"offset":990}}},{"type":"text","value":": This is an identifier for the criterion to which the test case applies. #-#-# stands for the number of that criterion, such as SC4-1-2.","position":{"start":{"line":22,"column":14,"offset":990},"end":{"line":22,"column":151,"offset":1127}}}],"position":{"start":{"line":22,"column":1,"offset":977},"end":{"line":23,"column":1,"offset":1128}}},{"type":"text","value":"\n"},{"type":"element","tagName":"li","properties":{},"children":[{"type":"element","tagName":"strong","properties":{},"children":[{"type":"text","value":"+SC#-#-#","position":{"start":{"line":24,"column":5,"offset":1133},"end":{"line":24,"column":13,"offset":1141}}}],"position":{"start":{"line":24,"column":3,"offset":1131},"end":{"line":24,"column":15,"offset":1143}}},{"type":"text","value":": This can be used if the test case applies to multiple success criteria, such as SC1-1-1+SC4-1-2-identifier. The numbers are in the same order as they are used in WCAG.","position":{"start":{"line":24,"column":15,"offset":1143},"end":{"line":24,"column":184,"offset":1312}}}],"position":{"start":{"line":24,"column":1,"offset":1129},"end":{"line":25,"column":1,"offset":1313}}},{"type":"text","value":"\n"},{"type":"element","tagName":"li","properties":{},"children":[{"type":"element","tagName":"strong","properties":{},"children":[{"type":"text","value":"identifier","position":{"start":{"line":26,"column":5,"offset":1318},"end":{"line":26,"column":15,"offset":1328}}}],"position":{"start":{"line":26,"column":3,"offset":1316},"end":{"line":26,"column":17,"offset":1330}}},{"type":"text","value":": This must be a lower case identifier of the test, preferably no more then 3 words. It can only contain alphanumeric values or a dash (-).","position":{"start":{"line":26,"column":17,"offset":1330},"end":{"line":26,"column":156,"offset":1469}}}],"position":{"start":{"line":26,"column":1,"offset":1314},"end":{"line":26,"column":156,"offset":1469}}},{"type":"text","value":"\n"}],"position":{"start":{"line":22,"column":1,"offset":977},"end":{"line":26,"column":156,"offset":1469}}},{"type":"text","value":"\n"},{"type":"element","tagName":"h3","properties":{"id":"test-aspects"},"children":[{"type":"element","tagName":"a","properties":{"href":"#test-aspects","aria-label":"test aspects permalink","class":"anchor"},"children":[{"type":"raw","value":"<svg aria-hidden=\"true\" focusable=\"false\" height=\"16\" version=\"1.1\" viewBox=\"0 0 16 16\" width=\"16\"><path fill-rule=\"evenodd\" d=\"M4 9h1v1H4c-1.5 0-3-1.69-3-3.5S2.55 3 4 3h4c1.45 0 3 1.69 3 3.5 0 1.41-.91 2.72-2 3.25V8.59c.58-.45 1-1.27 1-2.09C10 5.22 8.98 4 8 4H4c-.98 0-2 1.22-2 2.5S3 9 4 9zm9-3h-1v1h1c1 0 2 1.22 2 2.5S13.98 12 13 12H9c-.98 0-2-1.22-2-2.5 0-.83.42-1.64 1-2.09V6.25c-1.09.53-2 1.84-2 3.25C6 11.31 7.55 13 9 13h4c1.45 0 3-1.69 3-3.5S14.5 6 13 6z\"></path></svg>"}]},{"type":"text","value":"Test aspects","position":{"start":{"line":28,"column":5,"offset":1475},"end":{"line":28,"column":17,"offset":1487}}}],"position":{"start":{"line":28,"column":1,"offset":1471},"end":{"line":28,"column":17,"offset":1487}}},{"type":"text","value":"\n"},{"type":"element","tagName":"p","properties":{},"children":[{"type":"text","value":"A test aspect is a part of a test subject that must be available in order to properly run the test. The ACT Rules Format defines the following:","position":{"start":{"line":30,"column":1,"offset":1489},"end":{"line":30,"column":144,"offset":1632}}}],"position":{"start":{"line":30,"column":1,"offset":1489},"end":{"line":30,"column":144,"offset":1632}}},{"type":"text","value":"\n"},{"type":"element","tagName":"ul","properties":{},"children":[{"type":"text","value":"\n"},{"type":"element","tagName":"li","properties":{},"children":[{"type":"text","value":"HTTP Messages: All messages sent through HTTP(S)","position":{"start":{"line":32,"column":3,"offset":1636},"end":{"line":32,"column":51,"offset":1684}}}],"position":{"start":{"line":32,"column":1,"offset":1634},"end":{"line":32,"column":51,"offset":1684}}},{"type":"text","value":"\n"},{"type":"element","tagName":"li","properties":{},"children":[{"type":"text","value":"DOM Tree: The tree that HTML is parsed into","position":{"start":{"line":33,"column":3,"offset":1687},"end":{"line":33,"column":46,"offset":1730}}}],"position":{"start":{"line":33,"column":1,"offset":1685},"end":{"line":33,"column":46,"offset":1730}}},{"type":"text","value":"\n"},{"type":"element","tagName":"li","properties":{},"children":[{"type":"text","value":"CSS Styling: CSS applied to lay out and style the DOM Tree","position":{"start":{"line":34,"column":3,"offset":1733},"end":{"line":34,"column":61,"offset":1791}}}],"position":{"start":{"line":34,"column":1,"offset":1731},"end":{"line":34,"column":61,"offset":1791}}},{"type":"text","value":"\n"},{"type":"element","tagName":"li","properties":{},"children":[{"type":"text","value":"Accessibility Tree: The tree that user agents expose to the accessibility API","position":{"start":{"line":35,"column":3,"offset":1794},"end":{"line":35,"column":80,"offset":1871}}}],"position":{"start":{"line":35,"column":1,"offset":1792},"end":{"line":35,"column":80,"offset":1871}}},{"type":"text","value":"\n"}],"position":{"start":{"line":32,"column":1,"offset":1634},"end":{"line":35,"column":80,"offset":1871}}},{"type":"text","value":"\n"},{"type":"element","tagName":"p","properties":{},"children":[{"type":"text","value":"Other aspects may be necessary for testing. These can be added as long as they are sufficiently defined.","position":{"start":{"line":37,"column":1,"offset":1873},"end":{"line":37,"column":105,"offset":1977}}}],"position":{"start":{"line":37,"column":1,"offset":1873},"end":{"line":37,"column":105,"offset":1977}}},{"type":"text","value":"\n"},{"type":"element","tagName":"h3","properties":{"id":"authors"},"children":[{"type":"element","tagName":"a","properties":{"href":"#authors","aria-label":"authors permalink","class":"anchor"},"children":[{"type":"raw","value":"<svg aria-hidden=\"true\" focusable=\"false\" height=\"16\" version=\"1.1\" viewBox=\"0 0 16 16\" width=\"16\"><path fill-rule=\"evenodd\" d=\"M4 9h1v1H4c-1.5 0-3-1.69-3-3.5S2.55 3 4 3h4c1.45 0 3 1.69 3 3.5 0 1.41-.91 2.72-2 3.25V8.59c.58-.45 1-1.27 1-2.09C10 5.22 8.98 4 8 4H4c-.98 0-2 1.22-2 2.5S3 9 4 9zm9-3h-1v1h1c1 0 2 1.22 2 2.5S13.98 12 13 12H9c-.98 0-2-1.22-2-2.5 0-.83.42-1.64 1-2.09V6.25c-1.09.53-2 1.84-2 3.25C6 11.31 7.55 13 9 13h4c1.45 0 3-1.69 3-3.5S14.5 6 13 6z\"></path></svg>"}]},{"type":"text","value":"Authors","position":{"start":{"line":39,"column":5,"offset":1983},"end":{"line":39,"column":12,"offset":1990}}}],"position":{"start":{"line":39,"column":1,"offset":1979},"end":{"line":39,"column":12,"offset":1990}}},{"type":"text","value":"\n"},{"type":"element","tagName":"p","properties":{},"children":[{"type":"text","value":"Names of the Authors. These must be an exact match of names in ","position":{"start":{"line":41,"column":1,"offset":1992},"end":{"line":41,"column":64,"offset":2055}}},{"type":"raw","value":"<code class=\"language-text\">contributors</code>","position":{"start":{"line":41,"column":64,"offset":2055},"end":{"line":41,"column":78,"offset":2069}}},{"type":"text","value":" property in ","position":{"start":{"line":41,"column":78,"offset":2069},"end":{"line":41,"column":91,"offset":2082}}},{"type":"raw","value":"<code class=\"language-text\">package.json</code>","position":{"start":{"line":41,"column":91,"offset":2082},"end":{"line":41,"column":105,"offset":2096}}},{"type":"text","value":".","position":{"start":{"line":41,"column":105,"offset":2096},"end":{"line":41,"column":106,"offset":2097}}}],"position":{"start":{"line":41,"column":1,"offset":1992},"end":{"line":41,"column":106,"offset":2097}}},{"type":"text","value":"\n"},{"type":"element","tagName":"h2","properties":{"id":"assumptions"},"children":[{"type":"element","tagName":"a","properties":{"href":"#assumptions","aria-label":"assumptions permalink","class":"anchor"},"children":[{"type":"raw","value":"<svg aria-hidden=\"true\" focusable=\"false\" height=\"16\" version=\"1.1\" viewBox=\"0 0 16 16\" width=\"16\"><path fill-rule=\"evenodd\" d=\"M4 9h1v1H4c-1.5 0-3-1.69-3-3.5S2.55 3 4 3h4c1.45 0 3 1.69 3 3.5 0 1.41-.91 2.72-2 3.25V8.59c.58-.45 1-1.27 1-2.09C10 5.22 8.98 4 8 4H4c-.98 0-2 1.22-2 2.5S3 9 4 9zm9-3h-1v1h1c1 0 2 1.22 2 2.5S13.98 12 13 12H9c-.98 0-2-1.22-2-2.5 0-.83.42-1.64 1-2.09V6.25c-1.09.53-2 1.84-2 3.25C6 11.31 7.55 13 9 13h4c1.45 0 3-1.69 3-3.5S14.5 6 13 6z\"></path></svg>"}]},{"type":"text","value":"Assumptions","position":{"start":{"line":43,"column":4,"offset":2102},"end":{"line":43,"column":15,"offset":2113}}}],"position":{"start":{"line":43,"column":1,"offset":2099},"end":{"line":43,"column":15,"offset":2113}}},{"type":"text","value":"\n"},{"type":"element","tagName":"p","properties":{},"children":[{"type":"text","value":"Many accessibility evaluations (especially automated tools) make assumptions about the structure of the web content and the way in which (web) technologies are used. Such assumptions influence the outcome of a test. If the assumptions are made implicitly, it will be difficult to interpret the test result. Comparability and reproduction of results by other tools are limited. Therefore the WCAG-ACT-RULES-CG test include a list of all assumptions made by the design of the rule.","position":{"start":{"line":45,"column":1,"offset":2115},"end":{"line":45,"column":480,"offset":2594}}}],"position":{"start":{"line":45,"column":1,"offset":2115},"end":{"line":45,"column":480,"offset":2594}}},{"type":"text","value":"\n"},{"type":"element","tagName":"blockquote","properties":{},"children":[{"type":"text","value":"\n"},{"type":"element","tagName":"p","properties":{},"children":[{"type":"element","tagName":"em","properties":{},"children":[{"type":"text","value":"For example:","position":{"start":{"line":47,"column":4,"offset":2599},"end":{"line":47,"column":16,"offset":2611}}}],"position":{"start":{"line":47,"column":3,"offset":2598},"end":{"line":47,"column":17,"offset":2612}}},{"type":"text","value":" A rule for 1.4.1 Use of Color has to make an assumption with CSS-properties are used to make a link visually evident. Typically something like ","position":{"start":{"line":47,"column":17,"offset":2612},"end":{"line":47,"column":161,"offset":2756}}},{"type":"raw","value":"<code class=\"language-text\">background</code>","position":{"start":{"line":47,"column":161,"offset":2756},"end":{"line":47,"column":173,"offset":2768}}},{"type":"text","value":", ","position":{"start":{"line":47,"column":173,"offset":2768},"end":{"line":47,"column":175,"offset":2770}}},{"type":"raw","value":"<code class=\"language-text\">border</code>","position":{"start":{"line":47,"column":175,"offset":2770},"end":{"line":47,"column":183,"offset":2778}}},{"type":"text","value":", ","position":{"start":{"line":47,"column":183,"offset":2778},"end":{"line":47,"column":185,"offset":2780}}},{"type":"raw","value":"<code class=\"language-text\">color</code>","position":{"start":{"line":47,"column":185,"offset":2780},"end":{"line":47,"column":192,"offset":2787}}},{"type":"text","value":", ","position":{"start":{"line":47,"column":192,"offset":2787},"end":{"line":47,"column":194,"offset":2789}}},{"type":"raw","value":"<code class=\"language-text\">font</code>","position":{"start":{"line":47,"column":194,"offset":2789},"end":{"line":47,"column":200,"offset":2795}}},{"type":"text","value":", or ","position":{"start":{"line":47,"column":200,"offset":2795},"end":{"line":47,"column":205,"offset":2800}}},{"type":"raw","value":"<code class=\"language-text\">text-decoration</code>","position":{"start":{"line":47,"column":205,"offset":2800},"end":{"line":47,"column":222,"offset":2817}}},{"type":"text","value":".","position":{"start":{"line":47,"column":222,"offset":2817},"end":{"line":47,"column":223,"offset":2818}}}],"position":{"start":{"line":47,"column":3,"offset":2598},"end":{"line":47,"column":223,"offset":2818}}},{"type":"text","value":"\n"}],"position":{"start":{"line":47,"column":1,"offset":2596},"end":{"line":47,"column":223,"offset":2818}}},{"type":"text","value":"\n"},{"type":"element","tagName":"p","properties":{},"children":[{"type":"text","value":"While most assumptions relate to the rule itself, there are some assumptions that apply at other stages of the evaluation:","position":{"start":{"line":49,"column":1,"offset":2820},"end":{"line":49,"column":123,"offset":2942}}}],"position":{"start":{"line":49,"column":1,"offset":2820},"end":{"line":49,"column":123,"offset":2942}}},{"type":"text","value":"\n"},{"type":"element","tagName":"ul","properties":{},"children":[{"type":"text","value":"\n"},{"type":"element","tagName":"li","properties":{},"children":[{"type":"text","value":"It is assumed that the tested web page is the one that has to conform to WCAG 2.0 and that there is no ","position":{"start":{"line":51,"column":3,"offset":2946},"end":{"line":51,"column":106,"offset":3049}}},{"type":"element","tagName":"a","properties":{"href":"https://www.w3.org/TR/WCAG21/#dfn-conforming-alternate-version"},"children":[{"type":"text","value":"conforming alternative version","position":{"start":{"line":51,"column":107,"offset":3050},"end":{"line":51,"column":137,"offset":3080}}}],"position":{"start":{"line":51,"column":106,"offset":3049},"end":{"line":51,"column":202,"offset":3145}}},{"type":"text","value":".","position":{"start":{"line":51,"column":202,"offset":3145},"end":{"line":51,"column":203,"offset":3146}}}],"position":{"start":{"line":51,"column":1,"offset":2944},"end":{"line":52,"column":1,"offset":3147}}},{"type":"text","value":"\n"},{"type":"element","tagName":"li","properties":{},"children":[{"type":"text","value":"It is assumed that the following technologies are accessibility supported: HTML, CSS, WAI-ARIA, ... (See also WCAG-ACT-RULES-CG's ","position":{"start":{"line":53,"column":3,"offset":3150},"end":{"line":53,"column":133,"offset":3280}}},{"type":"element","tagName":"a","properties":{"href":"accessibility-support.html"},"children":[{"type":"text","value":"explanation on Accessibility Support","position":{"start":{"line":53,"column":134,"offset":3281},"end":{"line":53,"column":170,"offset":3317}}}],"position":{"start":{"line":53,"column":133,"offset":3280},"end":{"line":53,"column":199,"offset":3346}}},{"type":"text","value":").","position":{"start":{"line":53,"column":199,"offset":3346},"end":{"line":53,"column":201,"offset":3348}}}],"position":{"start":{"line":53,"column":1,"offset":3148},"end":{"line":53,"column":201,"offset":3348}}},{"type":"text","value":"\n"}],"position":{"start":{"line":51,"column":1,"offset":2944},"end":{"line":53,"column":201,"offset":3348}}},{"type":"text","value":"\n"},{"type":"element","tagName":"h2","properties":{"id":"applicability"},"children":[{"type":"element","tagName":"a","properties":{"href":"#applicability","aria-label":"applicability permalink","class":"anchor"},"children":[{"type":"raw","value":"<svg aria-hidden=\"true\" focusable=\"false\" height=\"16\" version=\"1.1\" viewBox=\"0 0 16 16\" width=\"16\"><path fill-rule=\"evenodd\" d=\"M4 9h1v1H4c-1.5 0-3-1.69-3-3.5S2.55 3 4 3h4c1.45 0 3 1.69 3 3.5 0 1.41-.91 2.72-2 3.25V8.59c.58-.45 1-1.27 1-2.09C10 5.22 8.98 4 8 4H4c-.98 0-2 1.22-2 2.5S3 9 4 9zm9-3h-1v1h1c1 0 2 1.22 2 2.5S13.98 12 13 12H9c-.98 0-2-1.22-2-2.5 0-.83.42-1.64 1-2.09V6.25c-1.09.53-2 1.84-2 3.25C6 11.31 7.55 13 9 13h4c1.45 0 3-1.69 3-3.5S14.5 6 13 6z\"></path></svg>"}]},{"type":"text","value":"Applicability","position":{"start":{"line":55,"column":4,"offset":3353},"end":{"line":55,"column":17,"offset":3366}}}],"position":{"start":{"line":55,"column":1,"offset":3350},"end":{"line":55,"column":17,"offset":3366}}},{"type":"text","value":"\n"},{"type":"element","tagName":"p","properties":{},"children":[{"type":"text","value":"Applicability describes which (elements of) web pages should be tested using the rule. These elements are known as test targets. Applicability must be written in plain language, so that it can be used by QA testers. Applicability must rely on well defined properties of the technologies that are tested. For example, a rule may be applicable to all ","position":{"start":{"line":57,"column":1,"offset":3368},"end":{"line":57,"column":350,"offset":3717}}},{"type":"raw","value":"<code class=\"language-text\">video</code>","position":{"start":{"line":57,"column":350,"offset":3717},"end":{"line":57,"column":357,"offset":3724}}},{"type":"text","value":" elements, but it can not be applicable to all ","position":{"start":{"line":57,"column":357,"offset":3724},"end":{"line":57,"column":404,"offset":3771}}},{"type":"raw","value":"<code class=\"language-text\">object</code>","position":{"start":{"line":57,"column":404,"offset":3771},"end":{"line":57,"column":412,"offset":3779}}},{"type":"text","value":" elements used to show video, unless the term \"video\" is further defined.","position":{"start":{"line":57,"column":412,"offset":3779},"end":{"line":57,"column":485,"offset":3852}}}],"position":{"start":{"line":57,"column":1,"offset":3368},"end":{"line":57,"column":485,"offset":3852}}},{"type":"text","value":"\n"},{"type":"element","tagName":"p","properties":{},"children":[{"type":"text","value":"Finding objective definitions to use in rules can be difficult, if not outright impossible in some cases. The intent here is to ensure repeatability of the rule. Not everything in WCAG testing is entirely repeatable, but when it comes to rule applicability, this is a hard requirement.","position":{"start":{"line":59,"column":1,"offset":3854},"end":{"line":59,"column":286,"offset":4139}}}],"position":{"start":{"line":59,"column":1,"offset":3854},"end":{"line":59,"column":286,"offset":4139}}},{"type":"text","value":"\n"},{"type":"element","tagName":"p","properties":{},"children":[{"type":"text","value":"For more details, see ","position":{"start":{"line":61,"column":1,"offset":4141},"end":{"line":61,"column":23,"offset":4163}}},{"type":"element","tagName":"a","properties":{"href":"https://w3c.github.io/wcag-act/act-rules-format.html#applicability"},"children":[{"type":"text","value":"ACT Rules Format: Applicability","position":{"start":{"line":61,"column":24,"offset":4164},"end":{"line":61,"column":55,"offset":4195}}}],"position":{"start":{"line":61,"column":23,"offset":4163},"end":{"line":61,"column":124,"offset":4264}}}],"position":{"start":{"line":61,"column":1,"offset":4141},"end":{"line":61,"column":124,"offset":4264}}},{"type":"text","value":"\n"},{"type":"element","tagName":"h2","properties":{"id":"expectations"},"children":[{"type":"element","tagName":"a","properties":{"href":"#expectations","aria-label":"expectations permalink","class":"anchor"},"children":[{"type":"raw","value":"<svg aria-hidden=\"true\" focusable=\"false\" height=\"16\" version=\"1.1\" viewBox=\"0 0 16 16\" width=\"16\"><path fill-rule=\"evenodd\" d=\"M4 9h1v1H4c-1.5 0-3-1.69-3-3.5S2.55 3 4 3h4c1.45 0 3 1.69 3 3.5 0 1.41-.91 2.72-2 3.25V8.59c.58-.45 1-1.27 1-2.09C10 5.22 8.98 4 8 4H4c-.98 0-2 1.22-2 2.5S3 9 4 9zm9-3h-1v1h1c1 0 2 1.22 2 2.5S13.98 12 13 12H9c-.98 0-2-1.22-2-2.5 0-.83.42-1.64 1-2.09V6.25c-1.09.53-2 1.84-2 3.25C6 11.31 7.55 13 9 13h4c1.45 0 3-1.69 3-3.5S14.5 6 13 6z\"></path></svg>"}]},{"type":"text","value":"Expectations","position":{"start":{"line":63,"column":4,"offset":4269},"end":{"line":63,"column":16,"offset":4281}}}],"position":{"start":{"line":63,"column":1,"offset":4266},"end":{"line":63,"column":16,"offset":4281}}},{"type":"text","value":"\n"},{"type":"element","tagName":"p","properties":{},"children":[{"type":"text","value":"The applicability help the testers (or test tools) identify what has to be checked. Following that, the expectations are statements that must be true for the applicable elements to pass the rule. If any of the expectations is false, than the target element failed the rule.","position":{"start":{"line":65,"column":1,"offset":4283},"end":{"line":65,"column":274,"offset":4556}}}],"position":{"start":{"line":65,"column":1,"offset":4283},"end":{"line":65,"column":274,"offset":4556}}},{"type":"text","value":"\n"},{"type":"element","tagName":"p","properties":{},"children":[{"type":"text","value":"Each expectation exposes a reason why an element may not meet a particular conformance requirement. The expectations can be \"linked\", in that one has to be met before a second can be tested. For example, a rule testing link names may have as its first expectation \"Target element has an accessible name\", and as a second expectation \"Expectation 1 is true for the target element, and the accessible name describes the function of the target element\".","position":{"start":{"line":67,"column":1,"offset":4558},"end":{"line":67,"column":451,"offset":5008}}}],"position":{"start":{"line":67,"column":1,"offset":4558},"end":{"line":67,"column":451,"offset":5008}}},{"type":"text","value":"\n"},{"type":"element","tagName":"p","properties":{},"children":[{"type":"text","value":"For more details, see ","position":{"start":{"line":69,"column":1,"offset":5010},"end":{"line":69,"column":23,"offset":5032}}},{"type":"element","tagName":"a","properties":{"href":"https://w3c.github.io/wcag-act/act-rules-format.html#expectations"},"children":[{"type":"text","value":"ACT Rules Format: Expectations","position":{"start":{"line":69,"column":24,"offset":5033},"end":{"line":69,"column":54,"offset":5063}}}],"position":{"start":{"line":69,"column":23,"offset":5032},"end":{"line":69,"column":122,"offset":5131}}}],"position":{"start":{"line":69,"column":1,"offset":5010},"end":{"line":69,"column":122,"offset":5131}}}],"position":{"start":{"line":1,"column":1,"offset":0},"end":{"line":70,"column":1,"offset":5132}}}}